[{"activityId":915333804776,"activityName":"Hinckley and Bosworth Walking","startTimeGMT":"2024-05-10 14:21:37","typeKey":"walking","distance":4191.85986328125,"duration":6410.35888671875,"calories":402,"bmrCalories":176,"averageHR":71,"maxHR":107,"steps":5712,"aerobicTrainingEffect":0.20000000298023224,"anaerobicTrainingEffect":0,"vO2MaxValue":51,"minTemperature":29,"maxTemperature":35,"locationName":"Hinckley and Bosworth"},{"activityId":915323842016,"activityName":"Hinckley and Bosworth Walking","startTimeGMT":"2024-05-10 14:21:37","typeKey":"walking","distance":4191.85986328125,"duration":6410.35888671875,"calories":402,"bmrCalories":176,"averageHR":71,"maxHR":107,"steps":5712,"aerobicTrainingEffect":0.20000000298023224,"anaerobicTrainingEffect":0,"vO2MaxValue":51,"minTemperature":29,"maxTemperature":35,"locationName":"Hinckley and Bosworth"},{"activityId":15315823191,"activityName":"Hinckley and Bosworth Walking","startTimeGMT":"2024-05-10 14:21:37","typeKey":"walking","distance":4191.85986328125,"duration":6410.35888671875,"calories":402,"bmrCalories":176,"averageHR":71,"maxHR":107,"steps":5712,"aerobicTrainingEffect":0.20000000298023224,"anaerobicTrainingEffect":0,"vO2MaxValue":51,"minTemperature":29,"maxTemperature":35,"locationName":"Hinckley and Bosworth"},{"activityId":15333804776,"activityName":"Hinckley and Bosworth Walking","startTimeGMT":"2024-05-10 14:21:37","typeKey":"walking","distance":4191.85986328125,"duration":6410.35888671875,"calories":402,"bmrCalories":176,"averageHR":71,"maxHR":107,"steps":5712,"aerobicTrainingEffect":0.20000000298023224,"anaerobicTrainingEffect":0,"vO2MaxValue":51,"minTemperature":29,"maxTemperature":35,"locationName":"Hinckley and Bosworth"},{"activityId":15323842016,"activityName":"Hinckley and Bosworth Walking","startTimeGMT":"2024-05-10 14:21:37","typeKey":"walking","distance":4191.85986328125,"duration":6410.35888671875,"calories":402,"bmrCalories":176,"averageHR":71,"maxHR":107,"steps":5712,"aerobicTrainingEffect":0.20000000298023224,"anaerobicTrainingEffect":0,"vO2MaxValue":51,"minTemperature":29,"maxTemperature":35,"locationName":"Hinckley and Bosworth"},{"activityId":153158231911,"activityName":"Hinckley and Bosworth Walking","startTimeGMT":"2024-05-10 14:21:37","typeKey":"walking","distance":4191.85986328125,"duration":6410.35888671875,"calories":402,"bmrCalories":176,"averageHR":71,"maxHR":107,"steps":5712,"aerobicTrainingEffect":0.20000000298023224,"anaerobicTrainingEffect":0,"vO2MaxValue":51,"minTemperature":29,"maxTemperature":35,"locationName":"Hinckley and Bosworth"},{"activityId":15351691106,"activityName":"Leicester Cardio","startTimeGMT":"2024-05-12 08:17:41","typeKey":"indoor_cardio","distance":5179.22998046875,"duration":4608.60693359375,"calories":586,"bmrCalories":127,"averageHR":107,"maxHR":137,"steps":2660,"aerobicTrainingEffect":1.2999999523162842,"anaerobicTrainingEffect":0,"vO2MaxValue":null,"minTemperature":26,"maxTemperature":29,"locationName":"Leicester"},{"activityId":15344694982,"activityName":"Charnwood Walking","startTimeGMT":"2024-05-11 18:58:03","typeKey":"walking","distance":2842.090087890625,"duration":2535.174072265625,"calories":237,"bmrCalories":70,"averageHR":85,"maxHR":114,"steps":3578,"aerobicTrainingEffect":0.5,"anaerobicTrainingEffect":0,"vO2MaxValue":51,"minTemperature":25,"maxTemperature":30,"locationName":"Charnwood"},{"activityId":15341481581,"activityName":"Blaby Walking","startTimeGMT":"2024-05-11 15:30:06","typeKey":"walking","distance":2967.929931640625,"duration":1877.739990234375,"calories":224,"bmrCalories":52,"averageHR":85,"maxHR":102,"steps":3344,"aerobicTrainingEffect":0.6000000238418579,"anaerobicTrainingEffect":0,"vO2MaxValue":51,"minTemperature":28,"maxTemperature":30,"locationName":"Blaby"},{"activityId":15358477023,"activityName":"Blaby Cycling","startTimeGMT":"2024-05-12 13:30:05","typeKey":"cycling","distance":49461.6015625,"duration":6624.16796875,"calories":1158,"bmrCalories":182,"averageHR":130,"maxHR":148,"steps":null,"aerobicTrainingEffect":3,"anaerobicTrainingEffect":0.20000000298023224,"vO2MaxValue":null,"minTemperature":27,"maxTemperature":33,"locationName":"Blaby"}]